odoo/addons/ddmrp_production_equivalent/README.rst
odoo/addons/ddmrp_production_equivalent/__init__.py
odoo/addons/ddmrp_production_equivalent/__manifest__.py
odoo/addons/ddmrp_production_equivalent/models/__init__.py
odoo/addons/ddmrp_production_equivalent/models/mrp_production.py
odoo/addons/ddmrp_production_equivalent/static/description/icon.png
odoo11_addon_ddmrp_production_equivalent-11.0.1.0.1.dist-info/DESCRIPTION.rst
odoo11_addon_ddmrp_production_equivalent-11.0.1.0.1.dist-info/METADATA
odoo11_addon_ddmrp_production_equivalent-11.0.1.0.1.dist-info/RECORD
odoo11_addon_ddmrp_production_equivalent-11.0.1.0.1.dist-info/WHEEL
odoo11_addon_ddmrp_production_equivalent-11.0.1.0.1.dist-info/metadata.json
odoo11_addon_ddmrp_production_equivalent-11.0.1.0.1.dist-info/top_level.txt
